{
  "results": [
    {
      "song_id": "song_01",
      "f1": 0.003842459173871278,
      "precision": 0.021621621621621623,
      "recall": 0.0021085925144965737,
      "ref_notes": 1897,
      "gen_notes": 185
    },
    {
      "song_id": "song_02",
      "f1": 0.0044742729306487695,
      "precision": 0.05063291139240506,
      "recall": 0.0023405500292568754,
      "ref_notes": 1709,
      "gen_notes": 79
    },
    {
      "song_id": "song_03",
      "f1": 0.0,
      "precision": 0.0,
      "recall": 0.0,
      "ref_notes": 1598,
      "gen_notes": 207
    },
    {
      "song_id": "song_04",
      "f1": 0.007662835249042146,
      "precision": 0.025362318840579712,
      "recall": 0.004513217279174726,
      "ref_notes": 1551,
      "gen_notes": 276
    },
    {
      "song_id": "song_05",
      "f1": 0.004395604395604396,
      "precision": 0.020689655172413793,
      "recall": 0.002459016393442623,
      "ref_notes": 1220,
      "gen_notes": 145
    },
    {
      "song_id": "song_06",
      "f1": 0.007186858316221767,
      "precision": 0.029411764705882353,
      "recall": 0.004093567251461989,
      "ref_notes": 1710,
      "gen_notes": 238
    },
    {
      "song_id": "song_07",
      "f1": 0.0017204301075268815,
      "precision": 0.017857142857142856,
      "recall": 0.0009037505648441031,
      "ref_notes": 2213,
      "gen_notes": 112
    },
    {
      "song_id": "song_08",
      "f1": 0.010309278350515464,
      "precision": 0.04054054054054054,
      "recall": 0.005905511811023622,
      "ref_notes": 1524,
      "gen_notes": 222
    }
  ],
  "summary": {
    "average_f1": 0.004948967315428838,
    "songs_above_70pct": 0,
    "min_f1": 0.0,
    "max_f1": 0.010309278350515464
  }
}
